spamfilter/__init__.py
spamfilter/filters/__init__.py
spamfilter/filters/_check_modes.py
spamfilter/filters/api.py
spamfilter/filters/blocklist.py
spamfilter/filters/blocklist_from_json.py
spamfilter/filters/bypass_detection.py
spamfilter/filters/capitals.py
spamfilter/filters/email.py
spamfilter/filters/filter.py
spamfilter/filters/length.py
spamfilter/filters/ml_text_classifier.py
spamfilter/filters/openai.py
spamfilter/filters/regex.py
spamfilter/filters/specialchars.py
spamfilter/filters/word_length.py
spamfilter/pipelines/__init__.py
spamfilter/premade/__init__.py
spamfilter/premade/_construct_pipeline.py
spamfilter/premade/article.py
spamfilter/premade/chat.py
spamfilter/result/__init__.py
spamfilter-3.0.0.dist-info/METADATA
spamfilter-3.0.0.dist-info/WHEEL
spamfilter-3.0.0.dist-info/licenses/LICENSE
spamfilter-3.0.0.dist-info/RECORD
