Metadata-Version: 2.4
Name: spamfilter
Version: 3.0.0
Summary: Create spam filtering and mitigation pipelines with ease using fully-customizable, object oriented components.
Project-URL: GitHub, https://github.com/mags0ft/spamfilter
Project-URL: Homepage, https://mags0ft.github.io/spamfilter/
Author-email: Magnus Schlinsog <magnusschlinsog@gmail.com>
License: Copyright 2023-2025 Magnus Schlinsog <magnusschlinsog@gmail.com> and GitHub contributors.
License-File: LICENSE
Keywords: anti spam,classification,spam,spam filter,spam mitigation,spam protection
Classifier: License :: OSI Approved :: MIT License
Classifier: Programming Language :: Python
Classifier: Programming Language :: Python :: 3
Requires-Python: >=3.9
Provides-Extra: api
Requires-Dist: requests; extra == 'api'
Provides-Extra: dev
Requires-Dist: mkdocs; extra == 'dev'
Requires-Dist: mkdocs-material; extra == 'dev'
Requires-Dist: mkdocstrings[python]; extra == 'dev'
Requires-Dist: pip-tools; extra == 'dev'
Requires-Dist: pylint; extra == 'dev'
Requires-Dist: pytest; extra == 'dev'
Requires-Dist: python-dotenv; extra == 'dev'
Provides-Extra: docs
Requires-Dist: mkdocs; extra == 'docs'
Requires-Dist: mkdocs-material; extra == 'docs'
Requires-Dist: mkdocstrings[python]; extra == 'docs'
Provides-Extra: openai
Requires-Dist: openai; extra == 'openai'
Provides-Extra: transformers
Requires-Dist: torch; extra == 'transformers'
Requires-Dist: transformers; extra == 'transformers'
